{"config": {"view": {"continuousWidth": 300, "continuousHeight": 300, "strokeWidth": 0}, "title": {"dx": 60, "dy": -15, "fontSize": 15}}, "data": {"name": "data-7a8d673402920f2ac896dfbb0534f61d"}, "mark": {"type": "bar"}, "encoding": {"color": {"field": "cat", "legend": {"labelFontSize": 12, "symbolSize": 400}, "scale": {"domain": [9.0, 2.0, 1.0, 0.0], "reverse": true, "scheme": "spectral"}, "title": null, "type": "nominal"}, "column": {"field": "seg2", "header": {"labelFontSize": 15}, "sort": {"field": "order"}, "title": null, "type": "nominal"}, "order": {"field": "order", "sort": "descending", "type": "quantitative"}, "row": {"field": "seg1", "header": {"labelFontSize": 15}, "sort": {"field": "order"}, "title": null, "type": "nominal"}, "tooltip": [{"field": "cat", "title": "Valor", "type": "nominal"}, {"field": "prop", "format": ".2%", "title": "Estimaci\u00f3n", "type": "quantitative"}, {"field": "lower", "format": ".2%", "title": "L\u00edmite inferior", "type": "quantitative"}, {"field": "upper", "format": ".2%", "title": "L\u00edmite superior", "type": "quantitative"}], "x": {"axis": {"labelAngle": 0, "labelFontSize": 11}, "field": "M", "sort": {"field": "order"}, "title": null, "type": "nominal"}, "y": {"axis": {"format": "%", "labelFontSize": 11}, "field": "prop", "scale": {"nice": false}, "title": null, "type": "quantitative"}}, "height": 175, "params": [{"name": "param_70", "select": {"type": "point", "fields": ["cat"], "on": "click", "toggle": "true"}, "bind": "legend"}, {"name": "param_71", "select": {"type": "interval", "encodings": ["x", "y"]}, "bind": "scales"}], "resolve": {"axis": {"x": "independent", "y": "independent"}}, "title": {"text": ["Poblaci\u00f3n seg\u00fan n\u00famero de personas con alguna limitaci\u00f3n  >=60 a\u00f1os en cada medici\u00f3n seg\u00fan sexo y edad (porcentajes e intervalos de", "confianza al 95%)"], "subtitle": "Fuente: Encuesta Sanitaria y Social de Andaluc\u00eda (Panel 1 en Medici\u00f3n 4). C\u00f3digo de variable: P12A1_3"}, "transform": [{"filter": {"param": "param_70"}}, {"filter": "indexof(datum.M, 'M') != -1"}], "width": 175, "$schema": "https://vega.github.io/schema/vega-lite/v5.8.0.json", "datasets": {"data-7a8d673402920f2ac896dfbb0534f61d": [{"M": "M2", "seg1": "Hombre", "seg2": "16-24", "cat": 9.0, "prop": 0.0, "lower": 0.0, "upper": 0.187365664060317, "order": 0}, {"M": "M2", "seg1": "Hombre", "seg2": "16-24", "cat": 2.0, "prop": 0.10331986564834217, "lower": 0.0, "upper": 0.4761888179942873, "order": 1}, {"M": "M2", "seg1": "Hombre", "seg2": "16-24", "cat": 1.0, "prop": 0.1736552017105887, "lower": 0.0, "upper": 0.6067460528713493, "order": 2}, {"M": "M2", "seg1": "Hombre", "seg2": "16-24", "cat": 0.0, "prop": 0.7230249326410692, "lower": 0.3441235535444324, "upper": 1.0, "order": 3}, {"M": "M2", "seg1": "Hombre", "seg2": "25-34", "cat": 9.0, "prop": 0.0, "lower": 0.0, "upper": 0.23246478161285578, "order": 4}, {"M": "M2", "seg1": "Hombre", "seg2": "25-34", "cat": 2.0, "prop": 0.1450290955976238, "lower": 0.0, "upper": 0.5828348813802915, "order": 5}, {"M": "M2", "seg1": "Hombre", "seg2": "25-34", "cat": 1.0, "prop": 0.1380971878077399, "lower": 0.0, "upper": 0.46931057184552566, "order": 6}, {"M": "M2", "seg1": "Hombre", "seg2": "25-34", "cat": 0.0, "prop": 0.7168737165946364, "lower": 0.2824433551963114, "upper": 1.0, "order": 7}, {"M": "M2", "seg1": "Hombre", "seg2": "35-44", "cat": 9.0, "prop": 0.0, "lower": 0.0, "upper": 0.2641728543221845, "order": 8}, {"M": "M2", "seg1": "Hombre", "seg2": "35-44", "cat": 2.0, "prop": 0.0, "lower": 0.0, "upper": 0.2641728543221845, "order": 9}, {"M": "M2", "seg1": "Hombre", "seg2": "35-44", "cat": 1.0, "prop": 0.17102079578391502, "lower": 0.0, "upper": 0.6557732565627322, "order": 10}, {"M": "M2", "seg1": "Hombre", "seg2": "35-44", "cat": 0.0, "prop": 0.828979204216085, "lower": 0.34263576722181177, "upper": 1.0, "order": 11}, {"M": "M2", "seg1": "Hombre", "seg2": "45-54", "cat": 9.0, "prop": 0.0, "lower": 0.0, "upper": 0.09987617963658278, "order": 12}, {"M": "M2", "seg1": "Hombre", "seg2": "45-54", "cat": 2.0, "prop": 0.0, "lower": 0.0, "upper": 0.09987617963658278, "order": 13}, {"M": "M2", "seg1": "Hombre", "seg2": "45-54", "cat": 1.0, "prop": 0.2741096899152317, "lower": 0.09639259774713423, "upper": 0.548654489842335, "order": 14}, {"M": "M2", "seg1": "Hombre", "seg2": "45-54", "cat": 0.0, "prop": 0.7258903100847681, "lower": 0.45134551015766494, "upper": 0.9036074022528657, "order": 15}, {"M": "M2", "seg1": "Hombre", "seg2": "55-64", "cat": 9.0, "prop": 0.0, "lower": 0.0, "upper": 0.07323939381115355, "order": 16}, {"M": "M2", "seg1": "Hombre", "seg2": "55-64", "cat": 2.0, "prop": 0.0, "lower": 0.0, "upper": 0.07323939381115355, "order": 17}, {"M": "M2", "seg1": "Hombre", "seg2": "55-64", "cat": 1.0, "prop": 0.39828679252454163, "lower": 0.2116050330583541, "upper": 0.6006545316913195, "order": 18}, {"M": "M2", "seg1": "Hombre", "seg2": "55-64", "cat": 0.0, "prop": 0.6017132074754583, "lower": 0.3993454683086805, "upper": 0.7883949669416458, "order": 19}, {"M": "M2", "seg1": "Hombre", "seg2": "65 Y MAS", "cat": 9.0, "prop": 0.0638160385162603, "lower": 0.0, "upper": 0.28676177674818326, "order": 20}, {"M": "M2", "seg1": "Hombre", "seg2": "65 Y MAS", "cat": 2.0, "prop": 0.1337262007017284, "lower": 0.0, "upper": 0.3822571307619887, "order": 21}, {"M": "M2", "seg1": "Hombre", "seg2": "65 Y MAS", "cat": 1.0, "prop": 0.6616549221868979, "lower": 0.36125742353100543, "upper": 0.8698086053724272, "order": 22}, {"M": "M2", "seg1": "Hombre", "seg2": "65 Y MAS", "cat": 0.0, "prop": 0.14080283859511328, "lower": 0.0, "upper": 0.43583300515076095, "order": 23}, {"M": "M2", "seg1": "Hombre", "seg2": "Total", "cat": 9.0, "prop": 0.0106511803020275, "lower": 0.0, "upper": 0.05991493030955789, "order": 24}, {"M": "M2", "seg1": "Hombre", "seg2": "Total", "cat": 2.0, "prop": 0.05452776399725401, "lower": 0.0154826608906887, "upper": 0.12794781960036258, "order": 25}, {"M": "M2", "seg1": "Hombre", "seg2": "Total", "cat": 1.0, "prop": 0.32524230657827174, "lower": 0.22126507238399715, "upper": 0.44123691271136206, "order": 26}, {"M": "M2", "seg1": "Hombre", "seg2": "Total", "cat": 0.0, "prop": 0.6095787491224467, "lower": 0.4810955449532265, "upper": 0.7223728878543544, "order": 27}, {"M": "M2", "seg1": "Mujer", "seg2": "16-24", "cat": 9.0, "prop": 0.0, "lower": 0.0, "upper": 0.187365664060317, "order": 28}, {"M": "M2", "seg1": "Mujer", "seg2": "16-24", "cat": 2.0, "prop": 0.0, "lower": 0.0, "upper": 0.187365664060317, "order": 29}, {"M": "M2", "seg1": "Mujer", "seg2": "16-24", "cat": 1.0, "prop": 0.10033296172279609, "lower": 0.0, "upper": 0.42460374948756013, "order": 30}, {"M": "M2", "seg1": "Mujer", "seg2": "16-24", "cat": 0.0, "prop": 0.899667038277204, "lower": 0.5751289856231272, "upper": 1.0, "order": 31}, {"M": "M2", "seg1": "Mujer", "seg2": "25-34", "cat": 9.0, "prop": 0.0, "lower": 0.0, "upper": 0.3057455846889496, "order": 32}, {"M": "M2", "seg1": "Mujer", "seg2": "25-34", "cat": 2.0, "prop": 0.0, "lower": 0.0, "upper": 0.3057455846889496, "order": 33}, {"M": "M2", "seg1": "Mujer", "seg2": "25-34", "cat": 1.0, "prop": 0.40263065639037954, "lower": 0.0, "upper": 1.0, "order": 34}, {"M": "M2", "seg1": "Mujer", "seg2": "25-34", "cat": 0.0, "prop": 0.5973693436096206, "lower": 0.17184083668165923, "upper": 1.0, "order": 35}, {"M": "M2", "seg1": "Mujer", "seg2": "35-44", "cat": 9.0, "prop": 0.0, "lower": 0.0, "upper": 0.10534757730523049, "order": 36}, {"M": "M2", "seg1": "Mujer", "seg2": "35-44", "cat": 2.0, "prop": 0.0, "lower": 0.0, "upper": 0.10534757730523049, "order": 37}, {"M": "M2", "seg1": "Mujer", "seg2": "35-44", "cat": 1.0, "prop": 0.2857401445704374, "lower": 0.10566951523030135, "upper": 0.5431780943109935, "order": 38}, {"M": "M2", "seg1": "Mujer", "seg2": "35-44", "cat": 0.0, "prop": 0.7142598554295625, "lower": 0.45682190568900655, "upper": 0.8943304847696986, "order": 39}, {"M": "M2", "seg1": "Mujer", "seg2": "45-54", "cat": 9.0, "prop": 0.0, "lower": 0.0, "upper": 0.070550756686437, "order": 40}, {"M": "M2", "seg1": "Mujer", "seg2": "45-54", "cat": 2.0, "prop": 0.11539519953528349, "lower": 0.03660504537671774, "upper": 0.299168694431494, "order": 41}, {"M": "M2", "seg1": "Mujer", "seg2": "45-54", "cat": 1.0, "prop": 0.22092936515683692, "lower": 0.10497235644153394, "upper": 0.4213173558204375, "order": 42}, {"M": "M2", "seg1": "Mujer", "seg2": "45-54", "cat": 0.0, "prop": 0.6636754353078795, "lower": 0.43965867661895247, "upper": 0.8197954549632934, "order": 43}, {"M": "M2", "seg1": "Mujer", "seg2": "55-64", "cat": 9.0, "prop": 0.0, "lower": 0.0, "upper": 0.10534757730523049, "order": 44}, {"M": "M2", "seg1": "Mujer", "seg2": "55-64", "cat": 2.0, "prop": 0.0, "lower": 0.0, "upper": 0.10534757730523049, "order": 45}, {"M": "M2", "seg1": "Mujer", "seg2": "55-64", "cat": 1.0, "prop": 0.7746163480356547, "lower": 0.5216685414960776, "upper": 0.946431568134654, "order": 46}, {"M": "M2", "seg1": "Mujer", "seg2": "55-64", "cat": 0.0, "prop": 0.2253836519643452, "lower": 0.05356843186534602, "upper": 0.4783314585039226, "order": 47}, {"M": "M2", "seg1": "Mujer", "seg2": "65 Y MAS", "cat": 9.0, "prop": 0.0, "lower": 0.0, "upper": 0.09494446892524806, "order": 48}, {"M": "M2", "seg1": "Mujer", "seg2": "65 Y MAS", "cat": 2.0, "prop": 0.03384822500061224, "lower": 0.0, "upper": 0.19184095314968788, "order": 49}, {"M": "M2", "seg1": "Mujer", "seg2": "65 Y MAS", "cat": 1.0, "prop": 0.8415504259859986, "lower": 0.6392930479403224, "upper": 0.9594455480536611, "order": 50}, {"M": "M2", "seg1": "Mujer", "seg2": "65 Y MAS", "cat": 0.0, "prop": 0.12460134901338908, "lower": 0.03517755143916036, "upper": 0.3357052481083838, "order": 51}, {"M": "M2", "seg1": "Mujer", "seg2": "Total", "cat": 9.0, "prop": 0.0, "lower": 0.0, "upper": 0.020386786790901005, "order": 52}, {"M": "M2", "seg1": "Mujer", "seg2": "Total", "cat": 2.0, "prop": 0.036464213755523465, "lower": 0.009250606793264464, "upper": 0.08457797492459615, "order": 53}, {"M": "M2", "seg1": "Mujer", "seg2": "Total", "cat": 1.0, "prop": 0.4834723229596314, "lower": 0.3785009324471979, "upper": 0.5919834373195728, "order": 54}, {"M": "M2", "seg1": "Mujer", "seg2": "Total", "cat": 0.0, "prop": 0.4800634632848451, "lower": 0.37403562974724075, "upper": 0.5847891015086868, "order": 55}, {"M": "M2", "seg1": "Total", "seg2": "16-24", "cat": 9.0, "prop": 0.0, "lower": 0.0, "upper": 0.09987617963658278, "order": 56}, {"M": "M2", "seg1": "Total", "seg2": "16-24", "cat": 2.0, "prop": 0.06087684271031039, "lower": 0.0, "upper": 0.26198160673912363, "order": 57}, {"M": "M2", "seg1": "Total", "seg2": "16-24", "cat": 1.0, "prop": 0.14353497754903427, "lower": 0.0, "upper": 0.44770241243387987, "order": 58}, {"M": "M2", "seg1": "Total", "seg2": "16-24", "cat": 0.0, "prop": 0.7955881797406553, "lower": 0.5039429091830985, "upper": 0.956541101528979, "order": 59}, {"M": "M2", "seg1": "Total", "seg2": "25-34", "cat": 9.0, "prop": 0.0, "lower": 0.0, "upper": 0.14505651819287643, "order": 60}, {"M": "M2", "seg1": "Total", "seg2": "25-34", "cat": 2.0, "prop": 0.09078040238474255, "lower": 0.0, "upper": 0.43647587154478373, "order": 61}, {"M": "M2", "seg1": "Total", "seg2": "25-34", "cat": 1.0, "prop": 0.23704695318098615, "lower": 0.07336467751265294, "upper": 0.5665427686264549, "order": 62}, {"M": "M2", "seg1": "Total", "seg2": "25-34", "cat": 0.0, "prop": 0.6721726444342713, "lower": 0.35931077837490044, "upper": 0.9175087139915025, "order": 63}, {"M": "M2", "seg1": "Total", "seg2": "35-44", "cat": 9.0, "prop": 0.0, "lower": 0.0, "upper": 0.07928168109333228, "order": 64}, {"M": "M2", "seg1": "Total", "seg2": "35-44", "cat": 2.0, "prop": 0.0, "lower": 0.0, "upper": 0.07928168109333228, "order": 65}, {"M": "M2", "seg1": "Total", "seg2": "35-44", "cat": 1.0, "prop": 0.23758503067536801, "lower": 0.07980895442311899, "upper": 0.44428816097105617, "order": 66}, {"M": "M2", "seg1": "Total", "seg2": "35-44", "cat": 0.0, "prop": 0.7624149693246319, "lower": 0.5557118390289439, "upper": 0.9201910455768806, "order": 67}, {"M": "M2", "seg1": "Total", "seg2": "45-54", "cat": 9.0, "prop": 0.0, "lower": 0.0, "upper": 0.04247623154155227, "order": 68}, {"M": "M2", "seg1": "Total", "seg2": "45-54", "cat": 2.0, "prop": 0.06694968227518636, "lower": 0.020418758567341655, "upper": 0.15944713794748655, "order": 69}, {"M": "M2", "seg1": "Total", "seg2": "45-54", "cat": 1.0, "prop": 0.2432556694689382, "lower": 0.14457505663158488, "upper": 0.3855268144256882, "order": 70}, {"M": "M2", "seg1": "Total", "seg2": "45-54", "cat": 0.0, "prop": 0.6897946482558753, "lower": 0.5504580255756085, "upper": 0.8109374587590311, "order": 71}, {"M": "M2", "seg1": "Total", "seg2": "55-64", "cat": 9.0, "prop": 0.0, "lower": 0.0, "upper": 0.04444144628689056, "order": 72}, {"M": "M2", "seg1": "Total", "seg2": "55-64", "cat": 2.0, "prop": 0.0, "lower": 0.0, "upper": 0.04444144628689056, "order": 73}, {"M": "M2", "seg1": "Total", "seg2": "55-64", "cat": 1.0, "prop": 0.5527886483369588, "lower": 0.3924816341748997, "upper": 0.6969644273880676, "order": 74}, {"M": "M2", "seg1": "Total", "seg2": "55-64", "cat": 0.0, "prop": 0.44721135166304127, "lower": 0.3030355726119324, "upper": 0.6075183658251007, "order": 75}, {"M": "M2", "seg1": "Total", "seg2": "65 Y MAS", "cat": 9.0, "prop": 0.02354087212716453, "lower": 0.0, "upper": 0.12693321028369786, "order": 76}, {"M": "M2", "seg1": "Total", "seg2": "65 Y MAS", "cat": 2.0, "prop": 0.07069185724364051, "lower": 0.01994075043422657, "upper": 0.19581774671874996, "order": 77}, {"M": "M2", "seg1": "Total", "seg2": "65 Y MAS", "cat": 1.0, "prop": 0.7751894115819562, "lower": 0.6088026907011536, "upper": 0.8971923512073745, "order": 78}, {"M": "M2", "seg1": "Total", "seg2": "65 Y MAS", "cat": 0.0, "prop": 0.1305778590472386, "lower": 0.046755833132216686, "upper": 0.25255759852253035, "order": 79}, {"M": "M2", "seg1": "Total", "seg2": "Total", "cat": 9.0, "prop": 0.005140730136484715, "lower": 0.0, "upper": 0.025807794916951562, "order": 80}, {"M": "M2", "seg1": "Total", "seg2": "Total", "cat": 2.0, "prop": 0.04518248107110854, "lower": 0.02122380986599451, "upper": 0.08345501909505491, "order": 81}, {"M": "M2", "seg1": "Total", "seg2": "Total", "cat": 1.0, "prop": 0.4071035271414545, "lower": 0.32664202535191145, "upper": 0.4875287457051996, "order": 82}, {"M": "M2", "seg1": "Total", "seg2": "Total", "cat": 0.0, "prop": 0.5425732616509521, "lower": 0.4648723121789995, "upper": 0.6214385051906627, "order": 83}, {"M": "M3", "seg1": "Hombre", "seg2": "16-24", "cat": 9.0, "prop": 0.0, "lower": 0.0, "upper": 0.23246478161285578, "order": 84}, {"M": "M3", "seg1": "Hombre", "seg2": "16-24", "cat": 2.0, "prop": 0.0, "lower": 0.0, "upper": 0.23246478161285578, "order": 85}, {"M": "M3", "seg1": "Hombre", "seg2": "16-24", "cat": 1.0, "prop": 0.0, "lower": 0.0, "upper": 0.23246478161285578, "order": 86}, {"M": "M3", "seg1": "Hombre", "seg2": "16-24", "cat": 0.0, "prop": 1.0, "lower": 0.7675352183871442, "upper": 1.0, "order": 87}, {"M": "M3", "seg1": "Hombre", "seg2": "25-34", "cat": 9.0, "prop": 0.0, "lower": 0.0, "upper": 0.17077310824484795, "order": 88}, {"M": "M3", "seg1": "Hombre", "seg2": "25-34", "cat": 2.0, "prop": 0.0, "lower": 0.0, "upper": 0.17077310824484795, "order": 89}, {"M": "M3", "seg1": "Hombre", "seg2": "25-34", "cat": 1.0, "prop": 0.22871237156376795, "lower": 0.0, "upper": 0.617994580701569, "order": 90}, {"M": "M3", "seg1": "Hombre", "seg2": "25-34", "cat": 0.0, "prop": 0.7712876284362321, "lower": 0.382005419298431, "upper": 1.0, "order": 91}, {"M": "M3", "seg1": "Hombre", "seg2": "35-44", "cat": 9.0, "prop": 0.0, "lower": 0.0, "upper": 0.2641728543221845, "order": 92}, {"M": "M3", "seg1": "Hombre", "seg2": "35-44", "cat": 2.0, "prop": 0.0, "lower": 0.0, "upper": 0.2641728543221845, "order": 93}, {"M": "M3", "seg1": "Hombre", "seg2": "35-44", "cat": 1.0, "prop": 0.18349829004949123, "lower": 0.0, "upper": 0.6631401984772243, "order": 94}, {"M": "M3", "seg1": "Hombre", "seg2": "35-44", "cat": 0.0, "prop": 0.8165017099505087, "lower": 0.33685264165848544, "upper": 1.0, "order": 95}, {"M": "M3", "seg1": "Hombre", "seg2": "45-54", "cat": 9.0, "prop": 0.0, "lower": 0.0, "upper": 0.0904764265378723, "order": 96}, {"M": "M3", "seg1": "Hombre", "seg2": "45-54", "cat": 2.0, "prop": 0.09329982053728006, "lower": 0.0, "upper": 0.32221928027332875, "order": 97}, {"M": "M3", "seg1": "Hombre", "seg2": "45-54", "cat": 1.0, "prop": 0.25447992867489017, "lower": 0.09342376591158273, "upper": 0.49252776758682515, "order": 98}, {"M": "M3", "seg1": "Hombre", "seg2": "45-54", "cat": 0.0, "prop": 0.65222025078783, "lower": 0.4042017949023477, "upper": 0.8502813240858993, "order": 99}, {"M": "M3", "seg1": "Hombre", "seg2": "55-64", "cat": 9.0, "prop": 0.0, "lower": 0.0, "upper": 0.0635512604767747, "order": 100}, {"M": "M3", "seg1": "Hombre", "seg2": "55-64", "cat": 2.0, "prop": 0.0, "lower": 0.0, "upper": 0.0635512604767747, "order": 101}, {"M": "M3", "seg1": "Hombre", "seg2": "55-64", "cat": 1.0, "prop": 0.47861976737602063, "lower": 0.3200947811919653, "upper": 0.6708685213277982, "order": 102}, {"M": "M3", "seg1": "Hombre", "seg2": "55-64", "cat": 0.0, "prop": 0.5213802326239794, "lower": 0.3291314786722018, "upper": 0.6799052188080351, "order": 103}, {"M": "M3", "seg1": "Hombre", "seg2": "65 Y MAS", "cat": 9.0, "prop": 0.0, "lower": 0.0, "upper": 0.1183066164528238, "order": 104}, {"M": "M3", "seg1": "Hombre", "seg2": "65 Y MAS", "cat": 2.0, "prop": 0.05444846579941597, "lower": 0.0, "upper": 0.23600229273871184, "order": 105}, {"M": "M3", "seg1": "Hombre", "seg2": "65 Y MAS", "cat": 1.0, "prop": 0.7063515643959002, "lower": 0.399296464729372, "upper": 0.9015193848670013, "order": 106}, {"M": "M3", "seg1": "Hombre", "seg2": "65 Y MAS", "cat": 0.0, "prop": 0.2391999698046839, "lower": 0.06025769459306596, "upper": 0.542717690091188, "order": 107}, {"M": "M3", "seg1": "Hombre", "seg2": "Total", "cat": 9.0, "prop": 0.0, "lower": 0.0, "upper": 0.021773347314387417, "order": 108}, {"M": "M3", "seg1": "Hombre", "seg2": "Total", "cat": 2.0, "prop": 0.025655188587038337, "lower": 0.0068762653855695575, "upper": 0.07066292076419452, "order": 109}, {"M": "M3", "seg1": "Hombre", "seg2": "Total", "cat": 1.0, "prop": 0.33496101249818117, "lower": 0.2355308185261534, "upper": 0.44613373717485805, "order": 110}, {"M": "M3", "seg1": "Hombre", "seg2": "Total", "cat": 0.0, "prop": 0.6393837989147804, "lower": 0.5301780105922111, "upper": 0.7435818654763441, "order": 111}, {"M": "M3", "seg1": "Mujer", "seg2": "16-24", "cat": 9.0, "prop": 0.0, "lower": 0.0, "upper": 0.23246478161285578, "order": 112}, {"M": "M3", "seg1": "Mujer", "seg2": "16-24", "cat": 2.0, "prop": 0.0, "lower": 0.0, "upper": 0.23246478161285578, "order": 113}, {"M": "M3", "seg1": "Mujer", "seg2": "16-24", "cat": 1.0, "prop": 0.10675599561919176, "lower": 0.0, "upper": 0.41087048399678544, "order": 114}, {"M": "M3", "seg1": "Mujer", "seg2": "16-24", "cat": 0.0, "prop": 0.8932440043808083, "lower": 0.5891295160032156, "upper": 1.0, "order": 115}, {"M": "M3", "seg1": "Mujer", "seg2": "25-34", "cat": 9.0, "prop": 0.0, "lower": 0.0, "upper": 0.569258531861899, "order": 116}, {"M": "M3", "seg1": "Mujer", "seg2": "25-34", "cat": 2.0, "prop": 0.0, "lower": 0.0, "upper": 0.569258531861899, "order": 117}, {"M": "M3", "seg1": "Mujer", "seg2": "25-34", "cat": 1.0, "prop": 0.5115786762597843, "lower": 0.0, "upper": 1.0, "order": 118}, {"M": "M3", "seg1": "Mujer", "seg2": "25-34", "cat": 0.0, "prop": 0.48842132374021574, "lower": 0.0, "upper": 1.0, "order": 119}, {"M": "M3", "seg1": "Mujer", "seg2": "35-44", "cat": 9.0, "prop": 0.0, "lower": 0.0, "upper": 0.14505651819287643, "order": 120}, {"M": "M3", "seg1": "Mujer", "seg2": "35-44", "cat": 2.0, "prop": 0.0, "lower": 0.0, "upper": 0.14505651819287643, "order": 121}, {"M": "M3", "seg1": "Mujer", "seg2": "35-44", "cat": 1.0, "prop": 0.16376778768952707, "lower": 0.0, "upper": 0.4703266713996163, "order": 122}, {"M": "M3", "seg1": "Mujer", "seg2": "35-44", "cat": 0.0, "prop": 0.8362322123104727, "lower": 0.5296733286003834, "upper": 1.0, "order": 123}, {"M": "M3", "seg1": "Mujer", "seg2": "45-54", "cat": 9.0, "prop": 0.0, "lower": 0.0, "upper": 0.070550756686437, "order": 124}, {"M": "M3", "seg1": "Mujer", "seg2": "45-54", "cat": 2.0, "prop": 0.045358421034327974, "lower": 0.0, "upper": 0.18480964523592178, "order": 125}, {"M": "M3", "seg1": "Mujer", "seg2": "45-54", "cat": 1.0, "prop": 0.2694662271801303, "lower": 0.11916145810620521, "upper": 0.47220189896997006, "order": 126}, {"M": "M3", "seg1": "Mujer", "seg2": "45-54", "cat": 0.0, "prop": 0.6851753517855417, "lower": 0.47759155509183504, "upper": 0.8356451285551629, "order": 127}, {"M": "M3", "seg1": "Mujer", "seg2": "55-64", "cat": 9.0, "prop": 0.0, "lower": 0.0, "upper": 0.07928168109333228, "order": 128}, {"M": "M3", "seg1": "Mujer", "seg2": "55-64", "cat": 2.0, "prop": 0.0375968482787441, "lower": 0.0, "upper": 0.19586216074202034, "order": 129}, {"M": "M3", "seg1": "Mujer", "seg2": "55-64", "cat": 1.0, "prop": 0.7072751661498444, "lower": 0.5013261717857417, "upper": 0.8732255542214483, "order": 130}, {"M": "M3", "seg1": "Mujer", "seg2": "55-64", "cat": 0.0, "prop": 0.2551279855714115, "lower": 0.10691694012393553, "upper": 0.45590430631002427, "order": 131}, {"M": "M3", "seg1": "Mujer", "seg2": "65 Y MAS", "cat": 9.0, "prop": 0.0, "lower": 0.0, "upper": 0.09494446892524806, "order": 132}, {"M": "M3", "seg1": "Mujer", "seg2": "65 Y MAS", "cat": 2.0, "prop": 0.0, "lower": 0.0, "upper": 0.09494446892524806, "order": 133}, {"M": "M3", "seg1": "Mujer", "seg2": "65 Y MAS", "cat": 1.0, "prop": 0.9196364510198227, "lower": 0.7674896407756295, "upper": 1.0, "order": 134}, {"M": "M3", "seg1": "Mujer", "seg2": "65 Y MAS", "cat": 0.0, "prop": 0.08036354898017709, "lower": 0.0, "upper": 0.23251035922436988, "order": 135}, {"M": "M3", "seg1": "Mujer", "seg2": "Total", "cat": 9.0, "prop": 0.0, "lower": 0.0, "upper": 0.02129066964074956, "order": 136}, {"M": "M3", "seg1": "Mujer", "seg2": "Total", "cat": 2.0, "prop": 0.018429411129928276, "lower": 0.0, "upper": 0.060674931865533174, "order": 137}, {"M": "M3", "seg1": "Mujer", "seg2": "Total", "cat": 1.0, "prop": 0.558859628310651, "lower": 0.43350917584174875, "upper": 0.6995055504832267, "order": 138}, {"M": "M3", "seg1": "Mujer", "seg2": "Total", "cat": 0.0, "prop": 0.42271096055942053, "lower": 0.2847534776085603, "upper": 0.5453142909814466, "order": 139}, {"M": "M3", "seg1": "Total", "seg2": "16-24", "cat": 9.0, "prop": 0.0, "lower": 0.0, "upper": 0.12605758342203194, "order": 140}, {"M": "M3", "seg1": "Total", "seg2": "16-24", "cat": 2.0, "prop": 0.0, "lower": 0.0, "upper": 0.12605758342203194, "order": 141}, {"M": "M3", "seg1": "Total", "seg2": "16-24", "cat": 1.0, "prop": 0.04363354475302961, "lower": 0.0, "upper": 0.19762764655329954, "order": 142}, {"M": "M3", "seg1": "Total", "seg2": "16-24", "cat": 0.0, "prop": 0.9563664552469705, "lower": 0.8023723534466997, "upper": 1.0, "order": 143}, {"M": "M3", "seg1": "Total", "seg2": "25-34", "cat": 9.0, "prop": 0.0, "lower": 0.0, "upper": 0.14505651819287643, "order": 144}, {"M": "M3", "seg1": "Total", "seg2": "25-34", "cat": 2.0, "prop": 0.0, "lower": 0.0, "upper": 0.14505651819287643, "order": 145}, {"M": "M3", "seg1": "Total", "seg2": "25-34", "cat": 1.0, "prop": 0.2547147622057763, "lower": 0.04372681791645867, "upper": 0.5497328501798896, "order": 146}, {"M": "M3", "seg1": "Total", "seg2": "25-34", "cat": 0.0, "prop": 0.7452852377942236, "lower": 0.45026714982011057, "upper": 0.9562731820835413, "order": 147}, {"M": "M3", "seg1": "Total", "seg2": "35-44", "cat": 9.0, "prop": 0.0, "lower": 0.0, "upper": 0.09987617963658278, "order": 148}, {"M": "M3", "seg1": "Total", "seg2": "35-44", "cat": 2.0, "prop": 0.0, "lower": 0.0, "upper": 0.09987617963658278, "order": 149}, {"M": "M3", "seg1": "Total", "seg2": "35-44", "cat": 1.0, "prop": 0.17386066114592477, "lower": 0.043725650514947076, "upper": 0.39846935938948136, "order": 150}, {"M": "M3", "seg1": "Total", "seg2": "35-44", "cat": 0.0, "prop": 0.8261393388540751, "lower": 0.6015306406105186, "upper": 0.956274349485053, "order": 151}, {"M": "M3", "seg1": "Total", "seg2": "45-54", "cat": 9.0, "prop": 0.0, "lower": 0.0, "upper": 0.04067743122308828, "order": 152}, {"M": "M3", "seg1": "Total", "seg2": "45-54", "cat": 2.0, "prop": 0.06716243283034781, "lower": 0.01806794506561203, "upper": 0.18424976113984656, "order": 153}, {"M": "M3", "seg1": "Total", "seg2": "45-54", "cat": 1.0, "prop": 0.2626503763127226, "lower": 0.14425516186466852, "upper": 0.39967455607492275, "order": 154}, {"M": "M3", "seg1": "Total", "seg2": "45-54", "cat": 0.0, "prop": 0.6701871908569296, "lower": 0.5347503468419369, "upper": 0.8005260793293636, "order": 155}, {"M": "M3", "seg1": "Total", "seg2": "55-64", "cat": 9.0, "prop": 0.0, "lower": 0.0, "upper": 0.036091987845995696, "order": 156}, {"M": "M3", "seg1": "Total", "seg2": "55-64", "cat": 2.0, "prop": 0.01677049338989368, "lower": 0.0, "upper": 0.08388713646069058, "order": 157}, {"M": "M3", "seg1": "Total", "seg2": "55-64", "cat": 1.0, "prop": 0.5806140575694329, "lower": 0.4442205551026246, "upper": 0.7236571584579546, "order": 158}, {"M": "M3", "seg1": "Total", "seg2": "55-64", "cat": 0.0, "prop": 0.4026154490406736, "lower": 0.2532177436337859, "upper": 0.5394083741351234, "order": 159}, {"M": "M3", "seg1": "Total", "seg2": "65 Y MAS", "cat": 9.0, "prop": 0.0, "lower": 0.0, "upper": 0.05453299154170082, "order": 160}, {"M": "M3", "seg1": "Total", "seg2": "65 Y MAS", "cat": 2.0, "prop": 0.017763202180243142, "lower": 0.0, "upper": 0.10697215981638306, "order": 161}, {"M": "M3", "seg1": "Total", "seg2": "65 Y MAS", "cat": 1.0, "prop": 0.850054645408477, "lower": 0.6909164759034383, "upper": 0.9439743658585874, "order": 162}, {"M": "M3", "seg1": "Total", "seg2": "65 Y MAS", "cat": 0.0, "prop": 0.1321821524112798, "lower": 0.050287459768474256, "upper": 0.30154201918964235, "order": 163}, {"M": "M3", "seg1": "Total", "seg2": "Total", "cat": 9.0, "prop": 0.0, "lower": 0.0, "upper": 0.01083856537074318, "order": 164}, {"M": "M3", "seg1": "Total", "seg2": "Total", "cat": 2.0, "prop": 0.022159645305789125, "lower": 0.007865353738798124, "upper": 0.05340343173032104, "order": 165}, {"M": "M3", "seg1": "Total", "seg2": "Total", "cat": 1.0, "prop": 0.44327424340375854, "lower": 0.35673821656914123, "upper": 0.5646600034408935, "order": 166}, {"M": "M3", "seg1": "Total", "seg2": "Total", "cat": 0.0, "prop": 0.5345661112904522, "lower": 0.42050076095302635, "upper": 0.6205497043527285, "order": 167}, {"M": "M4", "seg1": "Hombre", "seg2": "16-24", "cat": 9.0, "prop": 0.0, "lower": 0.0, "upper": 0.2641728543221845, "order": 168}, {"M": "M4", "seg1": "Hombre", "seg2": "16-24", "cat": 2.0, "prop": 0.0, "lower": 0.0, "upper": 0.2641728543221845, "order": 169}, {"M": "M4", "seg1": "Hombre", "seg2": "16-24", "cat": 1.0, "prop": 0.2141585384618831, "lower": 0.0, "upper": 0.6610262857698359, "order": 170}, {"M": "M4", "seg1": "Hombre", "seg2": "16-24", "cat": 0.0, "prop": 0.7858414615381167, "lower": 0.32905660083492955, "upper": 1.0, "order": 171}, {"M": "M4", "seg1": "Hombre", "seg2": "25-34", "cat": 9.0, "prop": 0.0, "lower": 0.0, "upper": 0.1568712305049839, "order": 172}, {"M": "M4", "seg1": "Hombre", "seg2": "25-34", "cat": 2.0, "prop": 0.0, "lower": 0.0, "upper": 0.1568712305049839, "order": 173}, {"M": "M4", "seg1": "Hombre", "seg2": "25-34", "cat": 1.0, "prop": 0.1350563611579429, "lower": 0.0, "upper": 0.4581717550464046, "order": 174}, {"M": "M4", "seg1": "Hombre", "seg2": "25-34", "cat": 0.0, "prop": 0.864943638842057, "lower": 0.5418282449535955, "upper": 1.0, "order": 175}, {"M": "M4", "seg1": "Hombre", "seg2": "35-44", "cat": 9.0, "prop": 0.0, "lower": 0.0, "upper": 0.3057455846889496, "order": 176}, {"M": "M4", "seg1": "Hombre", "seg2": "35-44", "cat": 2.0, "prop": 0.0, "lower": 0.0, "upper": 0.3057455846889496, "order": 177}, {"M": "M4", "seg1": "Hombre", "seg2": "35-44", "cat": 1.0, "prop": 0.07761159893534796, "lower": 0.0, "upper": 0.4522688819415607, "order": 178}, {"M": "M4", "seg1": "Hombre", "seg2": "35-44", "cat": 0.0, "prop": 0.922388401064652, "lower": 0.5477311180584393, "upper": 1.0, "order": 179}, {"M": "M4", "seg1": "Hombre", "seg2": "45-54", "cat": 9.0, "prop": 0.0, "lower": 0.0, "upper": 0.0904764265378723, "order": 180}, {"M": "M4", "seg1": "Hombre", "seg2": "45-54", "cat": 2.0, "prop": 0.061216072782265506, "lower": 0.0, "upper": 0.2593799937500482, "order": 181}, {"M": "M4", "seg1": "Hombre", "seg2": "45-54", "cat": 1.0, "prop": 0.2419495176452936, "lower": 0.08989987259356695, "upper": 0.483664112303514, "order": 182}, {"M": "M4", "seg1": "Hombre", "seg2": "45-54", "cat": 0.0, "prop": 0.6968344095724408, "lower": 0.45337210889283724, "upper": 0.8921474147484967, "order": 183}, {"M": "M4", "seg1": "Hombre", "seg2": "55-64", "cat": 9.0, "prop": 0.0, "lower": 0.0, "upper": 0.0635512604767747, "order": 184}, {"M": "M4", "seg1": "Hombre", "seg2": "55-64", "cat": 2.0, "prop": 0.027305146714779967, "lower": 0.0, "upper": 0.14614743328258656, "order": 185}, {"M": "M4", "seg1": "Hombre", "seg2": "55-64", "cat": 1.0, "prop": 0.6033526920939819, "lower": 0.43087313217142187, "upper": 0.7682328640907636, "order": 186}, {"M": "M4", "seg1": "Hombre", "seg2": "55-64", "cat": 0.0, "prop": 0.36934216119123814, "lower": 0.2112955468341525, "upper": 0.5406377308239323, "order": 187}, {"M": "M4", "seg1": "Hombre", "seg2": "65 Y MAS", "cat": 9.0, "prop": 0.0, "lower": 0.0, "upper": 0.1568712305049839, "order": 188}, {"M": "M4", "seg1": "Hombre", "seg2": "65 Y MAS", "cat": 2.0, "prop": 0.14976023084350773, "lower": 0.0, "upper": 0.4479604424139538, "order": 189}, {"M": "M4", "seg1": "Hombre", "seg2": "65 Y MAS", "cat": 1.0, "prop": 0.7570125719596442, "lower": 0.45002648492769537, "upper": 1.0, "order": 190}, {"M": "M4", "seg1": "Hombre", "seg2": "65 Y MAS", "cat": 0.0, "prop": 0.09322719719684801, "lower": 0.0, "upper": 0.43388794795705776, "order": 191}, {"M": "M4", "seg1": "Hombre", "seg2": "Total", "cat": 9.0, "prop": 0.0, "lower": 0.0, "upper": 0.023081537336826007, "order": 192}, {"M": "M4", "seg1": "Hombre", "seg2": "Total", "cat": 2.0, "prop": 0.03403255530139964, "lower": 0.010137829867386863, "upper": 0.08577809258328589, "order": 193}, {"M": "M4", "seg1": "Hombre", "seg2": "Total", "cat": 1.0, "prop": 0.33252847781542855, "lower": 0.20688705640804353, "upper": 0.4519492772369008, "order": 194}, {"M": "M4", "seg1": "Hombre", "seg2": "Total", "cat": 0.0, "prop": 0.6334389668831719, "lower": 0.5011173640251086, "upper": 0.7587492131077022, "order": 195}, {"M": "M4", "seg1": "Mujer", "seg2": "16-24", "cat": 9.0, "prop": 0.0, "lower": 0.0, "upper": 0.207508041680733, "order": 196}, {"M": "M4", "seg1": "Mujer", "seg2": "16-24", "cat": 2.0, "prop": 0.0, "lower": 0.0, "upper": 0.207508041680733, "order": 197}, {"M": "M4", "seg1": "Mujer", "seg2": "16-24", "cat": 1.0, "prop": 0.0, "lower": 0.0, "upper": 0.207508041680733, "order": 198}, {"M": "M4", "seg1": "Mujer", "seg2": "16-24", "cat": 0.0, "prop": 1.0, "lower": 0.792491958319267, "upper": 1.0, "order": 199}, {"M": "M4", "seg1": "Mujer", "seg2": "25-34", "cat": 9.0, "prop": 0.0, "lower": 0.0, "upper": 0.23246478161285578, "order": 200}, {"M": "M4", "seg1": "Mujer", "seg2": "25-34", "cat": 2.0, "prop": 0.0, "lower": 0.0, "upper": 0.23246478161285578, "order": 201}, {"M": "M4", "seg1": "Mujer", "seg2": "25-34", "cat": 1.0, "prop": 0.372395936687353, "lower": 0.09800336890867023, "upper": 0.7300758518680177, "order": 202}, {"M": "M4", "seg1": "Mujer", "seg2": "25-34", "cat": 0.0, "prop": 0.6276040633126471, "lower": 0.27026529428091295, "upper": 0.9019966310913298, "order": 203}, {"M": "M4", "seg1": "Mujer", "seg2": "35-44", "cat": 9.0, "prop": 0.0, "lower": 0.0, "upper": 0.1183066164528238, "order": 204}, {"M": "M4", "seg1": "Mujer", "seg2": "35-44", "cat": 2.0, "prop": 0.0, "lower": 0.0, "upper": 0.1183066164528238, "order": 205}, {"M": "M4", "seg1": "Mujer", "seg2": "35-44", "cat": 1.0, "prop": 0.1274898842713474, "lower": 0.0, "upper": 0.3716686034653253, "order": 206}, {"M": "M4", "seg1": "Mujer", "seg2": "35-44", "cat": 0.0, "prop": 0.8725101157286527, "lower": 0.6283313965346748, "upper": 1.0, "order": 207}, {"M": "M4", "seg1": "Mujer", "seg2": "45-54", "cat": 9.0, "prop": 0.0, "lower": 0.0, "upper": 0.0635512604767747, "order": 208}, {"M": "M4", "seg1": "Mujer", "seg2": "45-54", "cat": 2.0, "prop": 0.038311790164613106, "lower": 0.0, "upper": 0.18909565439797169, "order": 209}, {"M": "M4", "seg1": "Mujer", "seg2": "45-54", "cat": 1.0, "prop": 0.36364976672080196, "lower": 0.20571448229604314, "upper": 0.54969929643413, "order": 210}, {"M": "M4", "seg1": "Mujer", "seg2": "45-54", "cat": 0.0, "prop": 0.5980384431145851, "lower": 0.41653395524284176, "upper": 0.7645045647649021, "order": 211}, {"M": "M4", "seg1": "Mujer", "seg2": "55-64", "cat": 9.0, "prop": 0.0, "lower": 0.0, "upper": 0.10534757730523049, "order": 212}, {"M": "M4", "seg1": "Mujer", "seg2": "55-64", "cat": 2.0, "prop": 0.0, "lower": 0.0, "upper": 0.10534757730523049, "order": 213}, {"M": "M4", "seg1": "Mujer", "seg2": "55-64", "cat": 1.0, "prop": 0.7089050492171892, "lower": 0.43602078494257807, "upper": 0.8887706856317988, "order": 214}, {"M": "M4", "seg1": "Mujer", "seg2": "55-64", "cat": 0.0, "prop": 0.2910949507828107, "lower": 0.11122931436820102, "upper": 0.5639792150574219, "order": 215}, {"M": "M4", "seg1": "Mujer", "seg2": "65 Y MAS", "cat": 9.0, "prop": 0.0, "lower": 0.0, "upper": 0.13489289734181897, "order": 216}, {"M": "M4", "seg1": "Mujer", "seg2": "65 Y MAS", "cat": 2.0, "prop": 0.0, "lower": 0.0, "upper": 0.13489289734181897, "order": 217}, {"M": "M4", "seg1": "Mujer", "seg2": "65 Y MAS", "cat": 1.0, "prop": 0.8016055659134684, "lower": 0.5457789340074555, "upper": 0.9538765661632218, "order": 218}, {"M": "M4", "seg1": "Mujer", "seg2": "65 Y MAS", "cat": 0.0, "prop": 0.19839443408653154, "lower": 0.046123433836778, "upper": 0.45422106599254464, "order": 219}, {"M": "M4", "seg1": "Mujer", "seg2": "Total", "cat": 9.0, "prop": 0.0, "lower": 0.0, "upper": 0.02129066964074956, "order": 220}, {"M": "M4", "seg1": "Mujer", "seg2": "Total", "cat": 2.0, "prop": 0.010499300383016982, "lower": 0.0, "upper": 0.06406607041533129, "order": 221}, {"M": "M4", "seg1": "Mujer", "seg2": "Total", "cat": 1.0, "prop": 0.43988434950205063, "lower": 0.32988255859020515, "upper": 0.5758807795063643, "order": 222}, {"M": "M4", "seg1": "Mujer", "seg2": "Total", "cat": 0.0, "prop": 0.5496163501149323, "lower": 0.422762711533038, "upper": 0.6620931809050561, "order": 223}, {"M": "M4", "seg1": "Total", "seg2": "16-24", "cat": 9.0, "prop": 0.0, "lower": 0.0, "upper": 0.12605758342203194, "order": 224}, {"M": "M4", "seg1": "Total", "seg2": "16-24", "cat": 2.0, "prop": 0.0, "lower": 0.0, "upper": 0.12605758342203194, "order": 225}, {"M": "M4", "seg1": "Total", "seg2": "16-24", "cat": 1.0, "prop": 0.1254775430744379, "lower": 0.0, "upper": 0.3961686536573726, "order": 226}, {"M": "M4", "seg1": "Total", "seg2": "16-24", "cat": 0.0, "prop": 0.8745224569255621, "lower": 0.6038313463426284, "upper": 1.0, "order": 227}, {"M": "M4", "seg1": "Total", "seg2": "25-34", "cat": 9.0, "prop": 0.0, "lower": 0.0, "upper": 0.09987617963658278, "order": 228}, {"M": "M4", "seg1": "Total", "seg2": "25-34", "cat": 2.0, "prop": 0.0, "lower": 0.0, "upper": 0.09987617963658278, "order": 229}, {"M": "M4", "seg1": "Total", "seg2": "25-34", "cat": 1.0, "prop": 0.19919769464575737, "lower": 0.05277568730493792, "upper": 0.43558728245443123, "order": 230}, {"M": "M4", "seg1": "Total", "seg2": "25-34", "cat": 0.0, "prop": 0.8008023053542426, "lower": 0.5644127175455688, "upper": 0.9472243126950622, "order": 231}, {"M": "M4", "seg1": "Total", "seg2": "35-44", "cat": 9.0, "prop": 0.0, "lower": 0.0, "upper": 0.0904764265378723, "order": 232}, {"M": "M4", "seg1": "Total", "seg2": "35-44", "cat": 2.0, "prop": 0.0, "lower": 0.0, "upper": 0.0904764265378723, "order": 233}, {"M": "M4", "seg1": "Total", "seg2": "35-44", "cat": 1.0, "prop": 0.10090582856763865, "lower": 0.0, "upper": 0.2791295752799262, "order": 234}, {"M": "M4", "seg1": "Total", "seg2": "35-44", "cat": 0.0, "prop": 0.8990941714323614, "lower": 0.7208704247200739, "upper": 1.0, "order": 235}, {"M": "M4", "seg1": "Total", "seg2": "45-54", "cat": 9.0, "prop": 0.0, "lower": 0.0, "upper": 0.038247786892733435, "order": 236}, {"M": "M4", "seg1": "Total", "seg2": "45-54", "cat": 2.0, "prop": 0.047934495405632466, "lower": 0.0, "upper": 0.1678792098868024, "order": 237}, {"M": "M4", "seg1": "Total", "seg2": "45-54", "cat": 1.0, "prop": 0.31252021841049166, "lower": 0.18196100694376482, "upper": 0.4491376191894233, "order": 238}, {"M": "M4", "seg1": "Total", "seg2": "45-54", "cat": 0.0, "prop": 0.6395452861838758, "lower": 0.4964861599498786, "upper": 0.7786874387364388, "order": 239}, {"M": "M4", "seg1": "Total", "seg2": "55-64", "cat": 9.0, "prop": 0.0, "lower": 0.0, "upper": 0.04067743122308828, "order": 240}, {"M": "M4", "seg1": "Total", "seg2": "55-64", "cat": 2.0, "prop": 0.01698787444440005, "lower": 0.0, "upper": 0.08869010942538624, "order": 241}, {"M": "M4", "seg1": "Total", "seg2": "55-64", "cat": 1.0, "prop": 0.6432357375357792, "lower": 0.48957050941475755, "upper": 0.7723486931188263, "order": 242}, {"M": "M4", "seg1": "Total", "seg2": "55-64", "cat": 0.0, "prop": 0.33977638801982113, "lower": 0.2107898564145343, "upper": 0.4948596169511038, "order": 243}, {"M": "M4", "seg1": "Total", "seg2": "65 Y MAS", "cat": 9.0, "prop": 0.0, "lower": 0.0, "upper": 0.07614093175060478, "order": 244}, {"M": "M4", "seg1": "Total", "seg2": "65 Y MAS", "cat": 2.0, "prop": 0.05813591572382462, "lower": 0.0, "upper": 0.20489567291280925, "order": 245}, {"M": "M4", "seg1": "Total", "seg2": "65 Y MAS", "cat": 1.0, "prop": 0.7842948651768922, "lower": 0.6105126903280014, "upper": 0.9264406008052273, "order": 246}, {"M": "M4", "seg1": "Total", "seg2": "65 Y MAS", "cat": 0.0, "prop": 0.1575692190992832, "lower": 0.054646596716870346, "upper": 0.33421366573034833, "order": 247}, {"M": "M4", "seg1": "Total", "seg2": "Total", "cat": 9.0, "prop": 0.0, "lower": 0.0, "upper": 0.011153247074897394, "order": 248}, {"M": "M4", "seg1": "Total", "seg2": "Total", "cat": 2.0, "prop": 0.02319884221609011, "lower": 0.007562213457970427, "upper": 0.052132193678227697, "order": 249}, {"M": "M4", "seg1": "Total", "seg2": "Total", "cat": 1.0, "prop": 0.3819505707604916, "lower": 0.2838056858494174, "upper": 0.46858781708889785, "order": 250}, {"M": "M4", "seg1": "Total", "seg2": "Total", "cat": 0.0, "prop": 0.5948505870234182, "lower": 0.5039401604843927, "upper": 0.6931634357896098, "order": 251}]}}