{"config": {"view": {"continuousWidth": 300, "continuousHeight": 300}, "locale": {"number": {"decimal": ",", "thousands": ".", "grouping": [3], "currency": ["", "\u00a0\u20ac"]}}, "title": {"dx": 30, "dy": -15, "fontSize": 15}}, "vconcat": [{"facet": {"column": {"field": "seg2", "header": {"labelFontSize": 15}, "sort": {"field": "order"}, "title": null, "type": "nominal"}, "row": {"field": "row", "header": {"labels": false, "titleFontSize": 15, "titlePadding": 0}, "sort": {"field": "order"}, "title": "Absoluto (puntos porcentuales)", "type": "nominal"}}, "spec": {"layer": [{"mark": {"type": "rule"}, "encoding": {"y": {"aggregate": "mean", "field": "zero", "type": "quantitative"}}, "transform": [{"calculate": "0", "as": "zero"}]}, {"mark": {"type": "errorbar", "ticks": {"width": 10}}, "encoding": {"color": {"field": "seg1", "legend": {"labelFontSize": 12, "symbolSize": 400}, "sort": {"field": "order"}, "title": null, "type": "nominal"}, "tooltip": {"value": null}, "x": {"axis": {"labelAngle": 0, "labelExpr": "replace(datum.label, /M/g, '')", "labelFontSize": 11}, "field": "M", "sort": {"field": "order"}, "title": null, "type": "nominal"}, "xOffset": {"field": "seg1", "scale": {"paddingOuter": 0.5}, "sort": {"field": "order"}, "type": "nominal"}, "y": {"axis": {"labelFontSize": 11}, "field": "lower", "title": null, "type": "quantitative"}, "y2": {"field": "upper"}}}, {"mark": {"type": "line", "point": {"size": 50}}, "encoding": {"color": {"field": "seg1", "legend": {"labelFontSize": 12, "symbolSize": 400}, "sort": {"field": "order"}, "title": null, "type": "nominal"}, "tooltip": [{"field": "seg1", "title": "Grupo", "type": "nominal"}, {"field": "prop", "format": ".2f", "title": "Estimaci\u00f3n", "type": "quantitative"}, {"field": "lower", "format": ".2f", "title": "L\u00edmite inferior", "type": "quantitative"}, {"field": "upper", "format": ".2f", "title": "L\u00edmite superior", "type": "quantitative"}], "x": {"axis": {"labelAngle": 0, "labelExpr": "replace(datum.label, /M/g, '')", "labelFontSize": 11}, "field": "M", "sort": {"field": "order"}, "title": null, "type": "nominal"}, "xOffset": {"field": "seg1", "scale": {"paddingOuter": 0.5}, "sort": {"field": "order"}, "type": "nominal"}, "y": {"axis": {"labelFontSize": 11}, "field": "prop", "title": null, "type": "quantitative"}}, "name": "view_2733"}], "height": 175, "width": {"step": 45, "for": "position"}}, "resolve": {"axis": {"x": "independent", "y": "independent"}, "scale": {"xOffset": "independent"}}, "transform": [{"calculate": "datum.seg1 == 'Total'", "as": "row"}, {"filter": "datum.type == 'absolute'"}]}, {"facet": {"column": {"field": "seg2", "header": {"labelFontSize": 15}, "sort": {"field": "order"}, "title": null, "type": "nominal"}, "row": {"field": "row", "header": {"labels": false, "titleFontSize": 15, "titlePadding": 0}, "sort": {"field": "order"}, "title": "Relativo (%)", "type": "nominal"}}, "spec": {"layer": [{"mark": {"type": "rule"}, "encoding": {"y": {"aggregate": "mean", "field": "zero", "type": "quantitative"}}, "transform": [{"calculate": "0", "as": "zero"}]}, {"mark": {"type": "errorbar", "ticks": {"width": 10}}, "encoding": {"color": {"field": "seg1", "legend": {"labelFontSize": 12, "symbolSize": 400}, "sort": {"field": "order"}, "title": null, "type": "nominal"}, "tooltip": {"value": null}, "x": {"axis": {"labelAngle": 0, "labelExpr": "replace(datum.label, /M/g, '')", "labelFontSize": 11}, "field": "M", "sort": {"field": "order"}, "title": null, "type": "nominal"}, "xOffset": {"field": "seg1", "scale": {"paddingOuter": 0.5}, "sort": {"field": "order"}, "type": "nominal"}, "y": {"axis": {"labelFontSize": 11}, "field": "lower", "title": null, "type": "quantitative"}, "y2": {"field": "upper"}}}, {"mark": {"type": "line", "point": {"size": 50}}, "encoding": {"color": {"field": "seg1", "legend": {"labelFontSize": 12, "symbolSize": 400}, "sort": {"field": "order"}, "title": null, "type": "nominal"}, "tooltip": [{"field": "seg1", "title": "Grupo", "type": "nominal"}, {"field": "prop", "format": ".2f", "title": "Estimaci\u00f3n", "type": "quantitative"}, {"field": "lower", "format": ".2f", "title": "L\u00edmite inferior", "type": "quantitative"}, {"field": "upper", "format": ".2f", "title": "L\u00edmite superior", "type": "quantitative"}], "x": {"axis": {"labelAngle": 0, "labelExpr": "replace(datum.label, /M/g, '')", "labelFontSize": 11}, "field": "M", "sort": {"field": "order"}, "title": null, "type": "nominal"}, "xOffset": {"field": "seg1", "scale": {"paddingOuter": 0.5}, "sort": {"field": "order"}, "type": "nominal"}, "y": {"axis": {"labelFontSize": 11}, "field": "prop", "title": null, "type": "quantitative"}}, "name": "view_2734"}], "height": 175, "width": {"step": 45, "for": "position"}}, "resolve": {"axis": {"x": "independent", "y": "independent"}, "scale": {"xOffset": "independent"}}, "transform": [{"calculate": "datum.seg1 == 'Total'", "as": "row"}, {"filter": "datum.type == 'relative'"}]}], "data": {"name": "data-fcc4826cf697ce9fb7f17da1c8e75241"}, "params": [{"name": "param_3336", "select": {"type": "interval", "encodings": ["x", "y"]}, "bind": "scales", "views": ["view_2733"]}, {"name": "param_3337", "select": {"type": "interval", "encodings": ["x", "y"]}, "bind": "scales", "views": ["view_2734"]}], "title": {"text": ["Poblaci\u00f3n que ha consumido m\u00e1s alcohol respecto al \u00faltimo mes, cambio por medici\u00f3n, sexo", "y nivel de estudios (puntos porcentuales / porcentajes e intervalos de confianza al 95%)"], "subtitle": "Fuente: Encuesta Sanitaria y Social de Andaluc\u00eda (Panel 1 en Medici\u00f3n 4). C\u00f3digo de variable: P28A_2_R"}, "transform": [{"filter": "true == true"}], "$schema": "https://vega.github.io/schema/vega-lite/v5.20.1.json", "datasets": {"data-fcc4826cf697ce9fb7f17da1c8e75241": [{"type": "absolute", "M": "M2/M1", "seg1": "Hombre", "seg2": "Hasta primaria", "prop": -2.423968222062838, "lower": -11.300914624918201, "upper": 0.0, "order": 0}, {"type": "absolute", "M": "M2/M1", "seg1": "Hombre", "seg2": "Secundaria o FP grado sup", "prop": -0.14601546167199442, "lower": -6.410369170549902, "upper": 5.408087418991408, "order": 1}, {"type": "absolute", "M": "M2/M1", "seg1": "Hombre", "seg2": "Estudios universitarios o m\u00e1s", "prop": -4.235606848203008, "lower": -11.797978092563085, "upper": 2.1654391319026143, "order": 2}, {"type": "absolute", "M": "M2/M1", "seg1": "Hombre", "seg2": "No Pertenece a Medici\u00f3n", "prop": null, "lower": null, "upper": null, "order": 3}, {"type": "absolute", "M": "M2/M1", "seg1": "Hombre", "seg2": "Total", "prop": -2.0607720990057956, "lower": -6.256204486435413, "upper": 2.3387173754396064, "order": 4}, {"type": "absolute", "M": "M2/M1", "seg1": "Mujer", "seg2": "Hasta primaria", "prop": 0.0, "lower": null, "upper": null, "order": 5}, {"type": "absolute", "M": "M2/M1", "seg1": "Mujer", "seg2": "Secundaria o FP grado sup", "prop": -1.1639076641490802, "lower": -6.210447018536027, "upper": 3.4139505215425783, "order": 6}, {"type": "absolute", "M": "M2/M1", "seg1": "Mujer", "seg2": "Estudios universitarios o m\u00e1s", "prop": -0.2826255487425808, "lower": -5.606827712813626, "upper": 4.794326539093119, "order": 7}, {"type": "absolute", "M": "M2/M1", "seg1": "Mujer", "seg2": "No Pertenece a Medici\u00f3n", "prop": null, "lower": null, "upper": null, "order": 8}, {"type": "absolute", "M": "M2/M1", "seg1": "Mujer", "seg2": "Total", "prop": -0.6506361824331384, "lower": -3.5703474244929723, "upper": 2.5220811438099084, "order": 9}, {"type": "absolute", "M": "M2/M1", "seg1": "Total", "seg2": "Hasta primaria", "prop": -1.132746639987879, "lower": -6.1246312261270415, "upper": 0.0, "order": 10}, {"type": "absolute", "M": "M2/M1", "seg1": "Total", "seg2": "Secundaria o FP grado sup", "prop": -0.6814226710686773, "lower": -4.643615486662882, "upper": 3.195459751273117, "order": 11}, {"type": "absolute", "M": "M2/M1", "seg1": "Total", "seg2": "Estudios universitarios o m\u00e1s", "prop": -2.0357564567753714, "lower": -6.432628429492398, "upper": 2.0613847984680023, "order": 12}, {"type": "absolute", "M": "M2/M1", "seg1": "Total", "seg2": "No Pertenece a Medici\u00f3n", "prop": null, "lower": null, "upper": null, "order": 13}, {"type": "absolute", "M": "M2/M1", "seg1": "Total", "seg2": "Total", "prop": -1.3107074443079847, "lower": -3.8975502775501902, "upper": 1.2035784624938894, "order": 14}, {"type": "absolute", "M": "M3/M1", "seg1": "Hombre", "seg2": "Hasta primaria", "prop": -2.423968222062838, "lower": -11.300914624918201, "upper": 0.0, "order": 15}, {"type": "absolute", "M": "M3/M1", "seg1": "Hombre", "seg2": "Secundaria o FP grado sup", "prop": -6.328944957403982, "lower": -11.844570623868872, "upper": -1.9782583454727647, "order": 16}, {"type": "absolute", "M": "M3/M1", "seg1": "Hombre", "seg2": "Estudios universitarios o m\u00e1s", "prop": -10.220124425284272, "lower": -17.424495473482303, "upper": -5.361310717851488, "order": 17}, {"type": "absolute", "M": "M3/M1", "seg1": "Hombre", "seg2": "No Pertenece a Medici\u00f3n", "prop": null, "lower": null, "upper": null, "order": 18}, {"type": "absolute", "M": "M3/M1", "seg1": "Hombre", "seg2": "Total", "prop": -7.261794280172755, "lower": -10.882158416786925, "upper": -4.033196546785412, "order": 19}, {"type": "absolute", "M": "M3/M1", "seg1": "Mujer", "seg2": "Hasta primaria", "prop": 0.0, "lower": null, "upper": null, "order": 20}, {"type": "absolute", "M": "M3/M1", "seg1": "Mujer", "seg2": "Secundaria o FP grado sup", "prop": -4.585976052220324, "lower": -9.09989789338668, "upper": -1.0330902439177323, "order": 21}, {"type": "absolute", "M": "M3/M1", "seg1": "Mujer", "seg2": "Estudios universitarios o m\u00e1s", "prop": -5.3841008483454065, "lower": -10.235562178437773, "upper": -1.9959574849372856, "order": 22}, {"type": "absolute", "M": "M3/M1", "seg1": "Mujer", "seg2": "No Pertenece a Medici\u00f3n", "prop": null, "lower": null, "upper": null, "order": 23}, {"type": "absolute", "M": "M3/M1", "seg1": "Mujer", "seg2": "Total", "prop": -4.295750173156845, "lower": -7.026090872352799, "upper": -2.1124860800321037, "order": 24}, {"type": "absolute", "M": "M3/M1", "seg1": "Total", "seg2": "Hasta primaria", "prop": -1.132746639987879, "lower": -6.1246312261270415, "upper": 0.0, "order": 25}, {"type": "absolute", "M": "M3/M1", "seg1": "Total", "seg2": "Secundaria o FP grado sup", "prop": -5.42600070353594, "lower": -8.587156555261407, "upper": -2.4832315134537426, "order": 26}, {"type": "absolute", "M": "M3/M1", "seg1": "Total", "seg2": "Estudios universitarios o m\u00e1s", "prop": -7.5296433583405085, "lower": -11.746106895114524, "upper": -4.3964233674858, "order": 27}, {"type": "absolute", "M": "M3/M1", "seg1": "Total", "seg2": "No Pertenece a Medici\u00f3n", "prop": null, "lower": null, "upper": null, "order": 28}, {"type": "absolute", "M": "M3/M1", "seg1": "Total", "seg2": "Total", "prop": -5.6763600289328044, "lower": -7.785047382331978, "upper": -3.963976810279114, "order": 29}, {"type": "absolute", "M": "M4/M1", "seg1": "Hombre", "seg2": "Hasta primaria", "prop": 1.8677639734431306, "lower": -5.643552259190339, "upper": 10.765378230131038, "order": 30}, {"type": "absolute", "M": "M4/M1", "seg1": "Hombre", "seg2": "Secundaria o FP grado sup", "prop": -6.742722072231899, "lower": -12.27650026796378, "upper": -2.6877118252533116, "order": 31}, {"type": "absolute", "M": "M4/M1", "seg1": "Hombre", "seg2": "Estudios universitarios o m\u00e1s", "prop": -8.431935150643156, "lower": -16.242224866276285, "upper": -2.7390565596678527, "order": 32}, {"type": "absolute", "M": "M4/M1", "seg1": "Hombre", "seg2": "No Pertenece a Medici\u00f3n", "prop": null, "lower": null, "upper": null, "order": 33}, {"type": "absolute", "M": "M4/M1", "seg1": "Hombre", "seg2": "Total", "prop": -6.219076258385008, "lower": -10.02179467639375, "upper": -2.8421427755105864, "order": 34}, {"type": "absolute", "M": "M4/M1", "seg1": "Mujer", "seg2": "Hasta primaria", "prop": 0.0, "lower": null, "upper": null, "order": 35}, {"type": "absolute", "M": "M4/M1", "seg1": "Mujer", "seg2": "Secundaria o FP grado sup", "prop": -3.7628418304266162, "lower": -9.049094660104634, "upper": 0.05498524165385768, "order": 36}, {"type": "absolute", "M": "M4/M1", "seg1": "Mujer", "seg2": "Estudios universitarios o m\u00e1s", "prop": -4.545009916351189, "lower": -9.26930107581053, "upper": -0.5744434790322496, "order": 37}, {"type": "absolute", "M": "M4/M1", "seg1": "Mujer", "seg2": "No Pertenece a Medici\u00f3n", "prop": null, "lower": null, "upper": null, "order": 38}, {"type": "absolute", "M": "M4/M1", "seg1": "Mujer", "seg2": "Total", "prop": -3.6011245481550893, "lower": -6.373465921219361, "upper": -1.081776127186898, "order": 39}, {"type": "absolute", "M": "M4/M1", "seg1": "Total", "seg2": "Hasta primaria", "prop": 0.9382144578337607, "lower": -2.4896610883518666, "upper": 4.805109820403677, "order": 40}, {"type": "absolute", "M": "M4/M1", "seg1": "Total", "seg2": "Secundaria o FP grado sup", "prop": -5.236320722847002, "lower": -8.538347018398913, "upper": -2.2957279389245158, "order": 41}, {"type": "absolute", "M": "M4/M1", "seg1": "Total", "seg2": "Estudios universitarios o m\u00e1s", "prop": -6.260098336648248, "lower": -10.148466818844462, "upper": -2.596592508553334, "order": 42}, {"type": "absolute", "M": "M4/M1", "seg1": "Total", "seg2": "No Pertenece a Medici\u00f3n", "prop": null, "lower": null, "upper": null, "order": 43}, {"type": "absolute", "M": "M4/M1", "seg1": "Total", "seg2": "Total", "prop": -4.812308791242156, "lower": -7.085624159431444, "upper": -2.6735688998977736, "order": 44}, {"type": "relative", "M": "M2/M1", "seg1": "Hombre", "seg2": "Hasta primaria", "prop": -100.0, "lower": null, "upper": null, "order": 45}, {"type": "relative", "M": "M2/M1", "seg1": "Hombre", "seg2": "Secundaria o FP grado sup", "prop": -1.8510337217470207, "lower": -57.61117945403645, "upper": 101.67321011871483, "order": 46}, {"type": "relative", "M": "M2/M1", "seg1": "Hombre", "seg2": "Estudios universitarios o m\u00e1s", "prop": -38.78524028801223, "lower": -74.59759610025536, "upper": 39.36302086356751, "order": 47}, {"type": "relative", "M": "M2/M1", "seg1": "Hombre", "seg2": "No Pertenece a Medici\u00f3n", "prop": null, "lower": null, "upper": null, "order": 48}, {"type": "relative", "M": "M2/M1", "seg1": "Hombre", "seg2": "Total", "prop": -24.862846300603167, "lower": -58.256061140208026, "upper": 39.23474970795099, "order": 49}, {"type": "relative", "M": "M2/M1", "seg1": "Mujer", "seg2": "Hasta primaria", "prop": null, "lower": null, "upper": null, "order": 50}, {"type": "relative", "M": "M2/M1", "seg1": "Mujer", "seg2": "Secundaria o FP grado sup", "prop": -19.690043993601037, "lower": -76.65137464494327, "upper": 105.0038615616671, "order": 51}, {"type": "relative", "M": "M2/M1", "seg1": "Mujer", "seg2": "Estudios universitarios o m\u00e1s", "prop": -4.304842991644604, "lower": -64.160609661348, "upper": 109.24080688542979, "order": 52}, {"type": "relative", "M": "M2/M1", "seg1": "Mujer", "seg2": "No Pertenece a Medici\u00f3n", "prop": null, "lower": null, "upper": null, "order": 53}, {"type": "relative", "M": "M2/M1", "seg1": "Mujer", "seg2": "Total", "prop": -12.093759257250447, "lower": -52.850036328530415, "upper": 68.36443781466916, "order": 54}, {"type": "relative", "M": "M2/M1", "seg1": "Total", "seg2": "Hasta primaria", "prop": -100.0, "lower": null, "upper": null, "order": 55}, {"type": "relative", "M": "M2/M1", "seg1": "Total", "seg2": "Secundaria o FP grado sup", "prop": -9.922342326702891, "lower": -52.61705941460574, "upper": 60.67902112944683, "order": 56}, {"type": "relative", "M": "M2/M1", "seg1": "Total", "seg2": "Estudios universitarios o m\u00e1s", "prop": -23.965923761515086, "lower": -57.989473400449555, "upper": 39.53008491782079, "order": 57}, {"type": "relative", "M": "M2/M1", "seg1": "Total", "seg2": "No Pertenece a Medici\u00f3n", "prop": null, "lower": null, "upper": null, "order": 58}, {"type": "relative", "M": "M2/M1", "seg1": "Total", "seg2": "Total", "prop": -19.466305903830623, "lower": -47.02972426570787, "upper": 22.37711770543064, "order": 59}, {"type": "relative", "M": "M3/M1", "seg1": "Hombre", "seg2": "Hasta primaria", "prop": -100.0, "lower": null, "upper": null, "order": 60}, {"type": "relative", "M": "M3/M1", "seg1": "Hombre", "seg2": "Secundaria o FP grado sup", "prop": -80.23184945682003, "lower": -100.0, "upper": -5.897397706862549, "order": 61}, {"type": "relative", "M": "M3/M1", "seg1": "Hombre", "seg2": "Estudios universitarios o m\u00e1s", "prop": -93.58516874062691, "lower": -100.0, "upper": -56.68427497663745, "order": 62}, {"type": "relative", "M": "M3/M1", "seg1": "Hombre", "seg2": "No Pertenece a Medici\u00f3n", "prop": null, "lower": null, "upper": null, "order": 63}, {"type": "relative", "M": "M3/M1", "seg1": "Hombre", "seg2": "Total", "prop": -87.61224743951013, "lower": -97.31593728050673, "upper": -58.177348425410294, "order": 64}, {"type": "relative", "M": "M3/M1", "seg1": "Mujer", "seg2": "Hasta primaria", "prop": null, "lower": null, "upper": null, "order": 65}, {"type": "relative", "M": "M3/M1", "seg1": "Mujer", "seg2": "Secundaria o FP grado sup", "prop": -77.58181598351693, "lower": -100.0, "upper": 16.409275345195386, "order": 66}, {"type": "relative", "M": "M3/M1", "seg1": "Mujer", "seg2": "Estudios universitarios o m\u00e1s", "prop": -82.0085406518505, "lower": -100.0, "upper": -13.214149982528426, "order": 67}, {"type": "relative", "M": "M3/M1", "seg1": "Mujer", "seg2": "No Pertenece a Medici\u00f3n", "prop": null, "lower": null, "upper": null, "order": 68}, {"type": "relative", "M": "M3/M1", "seg1": "Mujer", "seg2": "Total", "prop": -79.84764731215907, "lower": -94.55757513669147, "upper": -37.55080885024471, "order": 69}, {"type": "relative", "M": "M3/M1", "seg1": "Total", "seg2": "Hasta primaria", "prop": -100.0, "lower": null, "upper": null, "order": 70}, {"type": "relative", "M": "M3/M1", "seg1": "Total", "seg2": "Secundaria o FP grado sup", "prop": -79.00916528206938, "lower": -93.42540555359462, "upper": -37.28812646222724, "order": 71}, {"type": "relative", "M": "M3/M1", "seg1": "Total", "seg2": "Estudios universitarios o m\u00e1s", "prop": -88.64265569528229, "lower": -96.8759602688115, "upper": -62.485065763996786, "order": 72}, {"type": "relative", "M": "M3/M1", "seg1": "Total", "seg2": "No Pertenece a Medici\u00f3n", "prop": null, "lower": null, "upper": null, "order": 73}, {"type": "relative", "M": "M3/M1", "seg1": "Total", "seg2": "Total", "prop": -84.30390871993743, "lower": -94.66580246896177, "upper": -68.96488951730866, "order": 74}, {"type": "relative", "M": "M4/M1", "seg1": "Hombre", "seg2": "Hasta primaria", "prop": 77.05397935677688, "lower": null, "upper": null, "order": 75}, {"type": "relative", "M": "M4/M1", "seg1": "Hombre", "seg2": "Secundaria o FP grado sup", "prop": -85.47728979624243, "lower": -100.0, "upper": -12.880579084939846, "order": 76}, {"type": "relative", "M": "M4/M1", "seg1": "Hombre", "seg2": "Estudios universitarios o m\u00e1s", "prop": -77.21080889492345, "lower": -95.24392611077309, "upper": -10.317322332851758, "order": 77}, {"type": "relative", "M": "M4/M1", "seg1": "Hombre", "seg2": "No Pertenece a Medici\u00f3n", "prop": null, "lower": null, "upper": null, "order": 78}, {"type": "relative", "M": "M4/M1", "seg1": "Hombre", "seg2": "Total", "prop": -75.03204125218595, "lower": -91.7063174780526, "upper": -31.462722044763574, "order": 79}, {"type": "relative", "M": "M4/M1", "seg1": "Mujer", "seg2": "Hasta primaria", "prop": null, "lower": null, "upper": null, "order": 80}, {"type": "relative", "M": "M4/M1", "seg1": "Mujer", "seg2": "Secundaria o FP grado sup", "prop": -63.656700152609666, "lower": -100.0, "upper": 41.51753197565794, "order": 81}, {"type": "relative", "M": "M4/M1", "seg1": "Mujer", "seg2": "Estudios universitarios o m\u00e1s", "prop": -69.22783227633896, "lower": -94.4463658966603, "upper": 39.113462759159255, "order": 82}, {"type": "relative", "M": "M4/M1", "seg1": "Mujer", "seg2": "No Pertenece a Medici\u00f3n", "prop": null, "lower": null, "upper": null, "order": 83}, {"type": "relative", "M": "M4/M1", "seg1": "Mujer", "seg2": "Total", "prop": -66.93623028755846, "lower": -88.79139047961196, "upper": -17.801477190410033, "order": 84}, {"type": "relative", "M": "M4/M1", "seg1": "Total", "seg2": "Hasta primaria", "prop": 82.82650547908932, "lower": null, "upper": null, "order": 85}, {"type": "relative", "M": "M4/M1", "seg1": "Total", "seg2": "Secundaria o FP grado sup", "prop": -76.24719421649509, "lower": -93.61978976107196, "upper": -28.819165306864914, "order": 86}, {"type": "relative", "M": "M4/M1", "seg1": "Total", "seg2": "Estudios universitarios o m\u00e1s", "prop": -73.69694885474888, "lower": -91.05149984759512, "upper": -37.03737528824062, "order": 87}, {"type": "relative", "M": "M4/M1", "seg1": "Total", "seg2": "No Pertenece a Medici\u00f3n", "prop": null, "lower": null, "upper": null, "order": 88}, {"type": "relative", "M": "M4/M1", "seg1": "Total", "seg2": "Total", "prop": -71.47123138792607, "lower": -86.85745047691415, "upper": -47.10035106687494, "order": 89}]}}